py_clocks/__init__.py
py_clocks/app.py
py_clocks/ui_core/panel.py
py_clocks/ui_core/ui_theme.py
py_clocks/ui_core/utils.py
py_clocks/ui_core/widgets/alarm_widget.py
py_clocks/ui_core/widgets/clock_widget.py
py_clocks/ui_core/widgets/stopwatch_widget.py
py_clocks/ui_core/widgets/timer_widget.py
py_clocks-26.0.0.dist-info/WHEEL
py_clocks-26.0.0.dist-info/METADATA
py_clocks-26.0.0.dist-info/RECORD
