Metadata-Version: 2.3
Name: py-clocks
Version: 26.0.0
Summary: The py-clocks package is a Python-based project designed for displaying multiple timezone clocks in windows desktop.
Keywords: python,clocks,timezone,desktop
Author: chaitu-ycr
Author-email: chaitu-ycr <chaitu.ycr@gmail.com>
License: MIT License
Classifier: Programming Language :: Python :: 3
Classifier: License :: OSI Approved :: MIT License
Classifier: Operating System :: Microsoft :: Windows
Requires-Dist: pyinstaller
Requires-Dist: pytz
Requires-Dist: nicegui[native]
Requires-Python: >=3.10, <=3.14
Project-URL: homepage, https://github.com/chaitu-ycr/py-clocks
Project-URL: repository, https://github.com/chaitu-ycr/py-clocks
Project-URL: documentation, https://chaitu-ycr.github.io/py-clocks
